CHANGES.txt
LICENSE.txt
MANIFEST.in
files.txt
requirements.txt
setup.py
SpotipyWebApi.egg-info/PKG-INFO
SpotipyWebApi.egg-info/SOURCES.txt
SpotipyWebApi.egg-info/dependency_links.txt
SpotipyWebApi.egg-info/requires.txt
SpotipyWebApi.egg-info/top_level.txt
spotipy/__init__.py
spotipy/oauth2.py
spotipy/spotipy.py
spotipy/util.py