Metadata-Version: 1.0
Name: SpotipyWebApi
Version: 1.320
Summary: simple client for the Spotify Web API
Home-page: http://github.com/plamere/spotipy
Author: @plamere
Author-email: paul@echonest.com
License: LICENSE.txt
Platform: UNKNOWN
